podsmith/__init__.py
podsmith/config_map.py
podsmith/image.py
podsmith/manifest.py
podsmith/pod.py
podsmith/pytest_plugin.py
podsmith/role.py
podsmith/role_binding.py
podsmith/service.py
podsmith/service_account.py
podsmith/session.py
podsmith-0.5.1.dist-info/entry_points.txt
podsmith-0.5.1.dist-info/licenses/LICENSE
podsmith-0.5.1.dist-info/WHEEL
podsmith-0.5.1.dist-info/METADATA
podsmith-0.5.1.dist-info/RECORD
