Metadata-Version: 2.4
Name: podsmith
Version: 0.5.1
Summary: **Podsmith** is a Python toolkit for managing Kubernetes-based test dependencies, enabling dynamic or pre-provisioned environments for integration testing.
Author-email: Andreas Stenius <andreas.stenius@gmail.com>
Requires-Python: >=3.10,<3.14
Classifier: Development Status :: 3 - Alpha
Classifier: Intended Audience :: Developers
Classifier: License :: OSI Approved :: MIT License
Classifier: Operating System :: OS Independent
Classifier: Programming Language :: Python :: 3.10
Classifier: Programming Language :: Python :: 3.11
Classifier: Programming Language :: Python :: 3.12
Classifier: Programming Language :: Python :: 3.13
Classifier: Topic :: Software Development :: Testing
Classifier: Topic :: Software Development :: Libraries
Classifier: Topic :: Software Development :: Build Tools
Classifier: Topic :: System :: Systems Administration
Classifier: Topic :: Utilities
License-File: LICENSE
Requires-Dist: backoff
Requires-Dist: docker
Requires-Dist: kubernetes
Requires-Dist: pytest
Requires-Dist: testcontainers
Requires-Dist: typing-extensions
Requires-Dist: urllib3
Project-URL: Repository, https://github.com/kaos/podsmith
